chessdata/__init__.py
chessdata/_nbdev.py
chessdata/engine.py
chessdata/etf.py
chessdata-0.0.3.dist-info/LICENSE
chessdata-0.0.3.dist-info/METADATA
chessdata-0.0.3.dist-info/WHEEL
chessdata-0.0.3.dist-info/entry_points.txt
chessdata-0.0.3.dist-info/top_level.txt
chessdata-0.0.3.dist-info/RECORD
