Metadata-Version: 2.1
Name: chessdata
Version: 0.0.3
Summary: Tools for analyzing chess data
Home-page: https://github.com/NateSolon/chessdata/tree/main/
Author: Nate Solon
Author-email: nate.solon@gmail.com
License: Apache Software License 2.0
Keywords: chess data analytics
Platform: UNKNOWN
Classifier: Development Status :: 3 - Alpha
Classifier: Intended Audience :: Developers
Classifier: Natural Language :: English
Classifier: Programming Language :: Python :: 3.7
Classifier: Programming Language :: Python :: 3.8
Classifier: License :: OSI Approved :: Apache Software License
Requires-Python: >=3.7
Requires-Dist: pip
Requires-Dist: packaging
Requires-Dist: pandas
Requires-Dist: chess (>=1.5.0)
Requires-Dist: python-lichess
Provides-Extra: dev
